STPyV8.py
_STPyV8.cpython-37m-x86_64-linux-gnu.so
st_pyv8-10.5.218.7.dist-info/LICENSE.txt
st_pyv8-10.5.218.7.dist-info/METADATA
st_pyv8-10.5.218.7.dist-info/WHEEL
st_pyv8-10.5.218.7.dist-info/top_level.txt
st_pyv8-10.5.218.7.dist-info/RECORD
